<objects>
<object><points><y>0.00097656</y><y>0.99805</y><x>0.0023952</x><x>0.9988</x></points><label>2</label><labelname>facade</labelname><flag>1</flag></object><object><points><y>0.16309</y><y>0.29297</y><x>0.16766</x><x>0.21916</x></points><label>3</label><labelname>window</labelname><flag>1</flag></object><object><points><y>0.16211</y><y>0.29199</y><x>0.050299</x><x>0.1018</x></points><label>3</label><labelname>window</labelname><flag>1</flag></object><object><points><y>0.16211</y><y>0.29199</y><x>0.29102</x><x>0.34251</x></points><label>3</label><labelname>window</labelname><flag>1</flag></object><object><points><y>0.16113</y><y>0.29004</y><x>0.41198</x><x>0.46467</x></points><label>3</label><labelname>window</labelname><flag>1</flag></object><object><points><y>0.16016</y><y>0.28906</y><x>0.53653</x><x>0.58802</x></points><label>3</label><labelname>window</labelname><flag>1</flag></object><object><points><y>0.16016</y><y>0.29004</y><x>0.65988</x><x>0.71138</x></points><label>3</label><labelname>window</labelname><flag>1</flag></object><object><points><y>0.16016</y><y>0.29004</y><x>0.78323</x><x>0.83473</x></points><label>3</label><labelname>window</labelname><flag>1</flag></object><object><points><y>0.16016</y><y>0.29004</y><x>0.90419</x><x>0.95569</x></points><label>3</label><labelname>window</labelname><flag>1</flag></object><object><points><y>0.3584</y><y>0.49414</y><x>0.8994</x><x>0.95449</x></points><label>3</label><labelname>window</labelname><flag>1</flag></object><object><points><y>0.3584</y><y>0.49414</y><x>0.77844</x><x>0.83353</x></points><label>3</label><labelname>window</labelname><flag>1</flag></object><object><points><y>0.35938</y><y>0.49512</y><x>0.65509</x><x>0.71018</x></points><label>3</label><labelname>window</labelname><flag>1</flag></object><object><points><y>0.3584</y><y>0.49414</y><x>0.53533</x><x>0.58922</x></points><label>3</label><labelname>window</labelname><flag>1</flag></object><object><points><y>0.36035</y><y>0.49609</y><x>0.41078</x><x>0.46587</x></points><label>3</label><labelname>window</labelname><flag>1</flag></object><object><points><y>0.35938</y><y>0.49609</y><x>0.28623</x><x>0.34132</x></points><label>3</label><labelname>window</labelname><flag>1</flag></object><object><points><y>0.35938</y><y>0.49512</y><x>0.16766</x><x>0.22156</x></points><label>3</label><labelname>window</labelname><flag>1</flag></object><object><points><y>0.55566</y><y>0.69238</y><x>0.28982</x><x>0.34491</x></points><label>3</label><labelname>window</labelname><flag>1</flag></object><object><points><y>0.55469</y><y>0.69043</y><x>0.41078</x><x>0.46467</x></points><label>3</label><labelname>window</labelname><flag>1</flag></object><object><points><y>0.55371</y><y>0.68945</y><x>0.16647</x><x>0.22156</x></points><label>3</label><labelname>window</labelname><flag>1</flag></object><object><points><y>0.55371</y><y>0.68945</y><x>0.53293</x><x>0.58683</x></points><label>3</label><labelname>window</labelname><flag>1</flag></object><object><points><y>0.55469</y><y>0.69043</y><x>0.65749</x><x>0.71138</x></points><label>3</label><labelname>window</labelname><flag>1</flag></object><object><points><y>0.55469</y><y>0.69043</y><x>0.77964</x><x>0.83353</x></points><label>3</label><labelname>window</labelname><flag>1</flag></object><object><points><y>0.55566</y><y>0.69238</y><x>0.9018</x><x>0.95689</x></points><label>3</label><labelname>window</labelname><flag>1</flag></object><object><points><y>0.36035</y><y>0.48535</y><x>0.049102</x><x>0.1006</x></points><label>3</label><labelname>window</labelname><flag>1</flag></object><object><points><y>0.55469</y><y>0.67969</y><x>0.049102</x><x>0.1018</x></points><label>3</label><labelname>window</labelname><flag>1</flag></object><object><points><y>0.77246</y><y>0.98438</y><x>0.75569</x><x>0.97006</x></points><label>3</label><labelname>window</labelname><flag>1</flag></object><object><points><y>0.77441</y><y>0.98145</y><x>0.51138</x><x>0.73174</x></points><label>3</label><labelname>window</labelname><flag>1</flag></object><object><points><y>0.21973</y><y>0.29004</y><x>0.010778</x><x>0.11018</x></points><label>7</label><labelname>balcony</labelname><flag>1</flag></object><object><points><y>0.42285</y><y>0.49316</y><x>0.0083832</x><x>0.10778</x></points><label>7</label><labelname>balcony</labelname><flag>1</flag></object><object><points><y>0.62402</y><y>0.68555</y><x>0.005988</x><x>0.11377</x></points><label>7</label><labelname>balcony</labelname><flag>1</flag></object><object><points><y>0.28418</y><y>0.33203</y><x>0.0071856</x><x>0.99042</x></points><label>10</label><labelname>molding</labelname><flag>1</flag></object><object><points><y>0.68066</y><y>0.76758</y><x>0.010778</x><x>0.99521</x></points><label>10</label><labelname>molding</labelname><flag>1</flag></object><object><points><y>0.49219</y><y>0.50977</y><x>0.010778</x><x>0.98922</x></points><label>10</label><labelname>molding</labelname><flag>1</flag></object><object><points><y>0.0068359</y><y>0.12207</y><x>0.0095808</x><x>0.99162</x></points><label>10</label><labelname>molding</labelname><flag>1</flag></object><object><points><y>0.050781</y><y>0.13086</y><x>0.2479</x><x>0.26707</x></points><label>9</label><labelname>deco</labelname><flag>1</flag></object><object><points><y>0.049805</y><y>0.13184</y><x>0.22994</x><x>0.2479</x></points><label>9</label><labelname>deco</labelname><flag>1</flag></object><object><points><y>0.049805</y><y>0.13184</y><x>0.12814</x><x>0.14611</x></points><label>9</label><labelname>deco</labelname><flag>1</flag></object><object><points><y>0.048828</y><y>0.13379</y><x>0.10898</x><x>0.12455</x></points><label>9</label><labelname>deco</labelname><flag>1</flag></object><object><points><y>0.049805</y><y>0.12988</y><x>0.3521</x><x>0.37126</x></points><label>9</label><labelname>deco</labelname><flag>1</flag></object><object><points><y>0.049805</y><y>0.13086</y><x>0.37246</x><x>0.39042</x></points><label>9</label><labelname>deco</labelname><flag>1</flag></object><object><points><y>0.051758</y><y>0.13184</y><x>0.020359</x><x>0.038323</x></points><label>9</label><labelname>deco</labelname><flag>1</flag></object><object><points><y>0.046875</y><y>0.12695</y><x>0.47305</x><x>0.49102</x></points><label>9</label><labelname>deco</labelname><flag>1</flag></object><object><points><y>0.046875</y><y>0.12793</y><x>0.49461</x><x>0.51257</x></points><label>9</label><labelname>deco</labelname><flag>1</flag></object><object><points><y>0.045898</y><y>0.12695</y><x>0.5976</x><x>0.61557</x></points><label>9</label><labelname>deco</labelname><flag>1</flag></object><object><points><y>0.045898</y><y>0.12695</y><x>0.61916</x><x>0.63713</x></points><label>9</label><labelname>deco</labelname><flag>1</flag></object><object><points><y>0.046875</y><y>0.12695</y><x>0.72335</x><x>0.74132</x></points><label>9</label><labelname>deco</labelname><flag>1</flag></object><object><points><y>0.046875</y><y>0.12695</y><x>0.74491</x><x>0.76287</x></points><label>9</label><labelname>deco</labelname><flag>1</flag></object><object><points><y>0.045898</y><y>0.12598</y><x>0.86467</x><x>0.88263</x></points><label>9</label><labelname>deco</labelname><flag>1</flag></object><object><points><y>0.044922</y><y>0.125</y><x>0.84431</x><x>0.86228</x></points><label>9</label><labelname>deco</labelname><flag>1</flag></object><object><points><y>0.046875</y><y>0.12793</y><x>0.9509</x><x>0.96886</x></points><label>9</label><labelname>deco</labelname><flag>1</flag></object><object><points><y>0.047852</y><y>0.12891</y><x>0.97365</x><x>0.99162</x></points><label>9</label><labelname>deco</labelname><flag>1</flag></object><object><points><y>0.052734</y><y>0.095703</y><x>0.88982</x><x>0.90419</x></points><label>9</label><labelname>deco</labelname><flag>1</flag></object><object><points><y>0.052734</y><y>0.095703</y><x>0.91377</x><x>0.92695</x></points><label>9</label><labelname>deco</labelname><flag>1</flag></object><object><points><y>0.053711</y><y>0.09668</y><x>0.93413</x><x>0.94731</x></points><label>9</label><labelname>deco</labelname><flag>1</flag></object><object><points><y>0.052734</y><y>0.095703</y><x>0.82635</x><x>0.84072</x></points><label>9</label><labelname>deco</labelname><flag>1</flag></object><object><points><y>0.053711</y><y>0.09668</y><x>0.80838</x><x>0.82156</x></points><label>9</label><labelname>deco</labelname><flag>1</flag></object><object><points><y>0.052734</y><y>0.095703</y><x>0.78683</x><x>0.8012</x></points><label>9</label><labelname>deco</labelname><flag>1</flag></object><object><points><y>0.052734</y><y>0.095703</y><x>0.76886</x><x>0.78204</x></points><label>9</label><labelname>deco</labelname><flag>1</flag></object><object><points><y>0.051758</y><y>0.094727</y><x>0.70539</x><x>0.71856</x></points><label>9</label><labelname>deco</labelname><flag>1</flag></object><object><points><y>0.054688</y><y>0.097656</y><x>0.68503</x><x>0.6982</x></points><label>9</label><labelname>deco</labelname><flag>1</flag></object><object><points><y>0.054688</y><y>0.097656</y><x>0.66347</x><x>0.67665</x></points><label>9</label><labelname>deco</labelname><flag>1</flag></object><object><points><y>0.053711</y><y>0.09668</y><x>0.64192</x><x>0.65509</x></points><label>9</label><labelname>deco</labelname><flag>1</flag></object><object><points><y>0.053711</y><y>0.09668</y><x>0.57844</x><x>0.59281</x></points><label>9</label><labelname>deco</labelname><flag>1</flag></object><object><points><y>0.053711</y><y>0.09668</y><x>0.55808</x><x>0.57246</x></points><label>9</label><labelname>deco</labelname><flag>1</flag></object><object><points><y>0.053711</y><y>0.09668</y><x>0.54012</x><x>0.55449</x></points><label>9</label><labelname>deco</labelname><flag>1</flag></object><object><points><y>0.053711</y><y>0.09668</y><x>0.51856</x><x>0.53174</x></points><label>9</label><labelname>deco</labelname><flag>1</flag></object><object><points><y>0.052734</y><y>0.095703</y><x>0.45629</x><x>0.46946</x></points><label>9</label><labelname>deco</labelname><flag>1</flag></object><object><points><y>0.053711</y><y>0.09668</y><x>0.43473</x><x>0.4491</x></points><label>9</label><labelname>deco</labelname><flag>1</flag></object><object><points><y>0.053711</y><y>0.09668</y><x>0.41916</x><x>0.43234</x></points><label>9</label><labelname>deco</labelname><flag>1</flag></object><object><points><y>0.054688</y><y>0.09668</y><x>0.39641</x><x>0.41078</x></points><label>9</label><labelname>deco</labelname><flag>1</flag></object><object><points><y>0.054688</y><y>0.097656</y><x>0.33293</x><x>0.34611</x></points><label>9</label><labelname>deco</labelname><flag>1</flag></object><object><points><y>0.054688</y><y>0.097656</y><x>0.31497</x><x>0.32934</x></points><label>9</label><labelname>deco</labelname><flag>1</flag></object><object><points><y>0.054688</y><y>0.09668</y><x>0.29222</x><x>0.30659</x></points><label>9</label><labelname>deco</labelname><flag>1</flag></object><object><points><y>0.054688</y><y>0.097656</y><x>0.27425</x><x>0.28743</x></points><label>9</label><labelname>deco</labelname><flag>1</flag></object><object><points><y>0.054688</y><y>0.097656</y><x>0.21198</x><x>0.22635</x></points><label>9</label><labelname>deco</labelname><flag>1</flag></object><object><points><y>0.054688</y><y>0.097656</y><x>0.19281</x><x>0.20599</x></points><label>9</label><labelname>deco</labelname><flag>1</flag></object><object><points><y>0.055664</y><y>0.098633</y><x>0.17246</x><x>0.18563</x></points><label>9</label><labelname>deco</labelname><flag>1</flag></object><object><points><y>0.054688</y><y>0.097656</y><x>0.1521</x><x>0.16647</x></points><label>9</label><labelname>deco</labelname><flag>1</flag></object><object><points><y>0.056641</y><y>0.099609</y><x>0.08982</x><x>0.10419</x></points><label>9</label><labelname>deco</labelname><flag>1</flag></object><object><points><y>0.056641</y><y>0.099609</y><x>0.069461</x><x>0.083832</x></points><label>9</label><labelname>deco</labelname><flag>1</flag></object><object><points><y>0.056641</y><y>0.099609</y><x>0.045509</x><x>0.05988</x></points><label>9</label><labelname>deco</labelname><flag>1</flag></object><object><points><y>0.69141</y><y>0.75977</y><x>0.75329</x><x>0.91976</x></points><label>12</label><labelname>shop</labelname><flag>1</flag></object>
</objects>
