<objects>
<object><points><y>0.0021645</y><y>0.98268</y><x>0.092958</x><x>0.93803</x></points><label>2</label><labelname>facade</labelname><flag>1</flag></object><object><points><y>0.13203</y><y>0.19481</y><x>0.40282</x><x>0.45915</x></points><label>3</label><labelname>window</labelname><flag>1</flag></object><object><points><y>0.12987</y><y>0.19481</y><x>0.46479</x><x>0.50986</x></points><label>3</label><labelname>window</labelname><flag>1</flag></object><object><points><y>0.11472</y><y>0.18398</y><x>0.72676</x><x>0.77465</x></points><label>3</label><labelname>window</labelname><flag>1</flag></object><object><points><y>0.11688</y><y>0.18831</y><x>0.66479</x><x>0.71268</x></points><label>3</label><labelname>window</labelname><flag>1</flag></object><object><points><y>0.28139</y><y>0.36797</y><x>0.75493</x><x>0.80563</x></points><label>3</label><labelname>window</labelname><flag>1</flag></object><object><points><y>0.28139</y><y>0.36797</y><x>0.69014</x><x>0.74366</x></points><label>3</label><labelname>window</labelname><flag>1</flag></object><object><points><y>0.28571</y><y>0.37446</y><x>0.39155</x><x>0.44225</x></points><label>3</label><labelname>window</labelname><flag>1</flag></object><object><points><y>0.28571</y><y>0.37446</y><x>0.32394</x><x>0.37746</x></points><label>3</label><labelname>window</labelname><flag>1</flag></object><object><points><y>0.28571</y><y>0.37446</y><x>0.2507</x><x>0.30423</x></points><label>3</label><labelname>window</labelname><flag>1</flag></object><object><points><y>0.28571</y><y>0.37229</y><x>0.19155</x><x>0.24507</x></points><label>3</label><labelname>window</labelname><flag>1</flag></object><object><points><y>0.47186</y><y>0.56061</y><x>0.26761</x><x>0.32113</x></points><label>3</label><labelname>window</labelname><flag>1</flag></object><object><points><y>0.47186</y><y>0.56061</y><x>0.32958</x><x>0.38028</x></points><label>3</label><labelname>window</labelname><flag>1</flag></object><object><points><y>0.46537</y><y>0.55411</y><x>0.68732</x><x>0.73803</x></points><label>3</label><labelname>window</labelname><flag>1</flag></object><object><points><y>0.46537</y><y>0.55195</y><x>0.7493</x><x>0.80282</x></points><label>3</label><labelname>window</labelname><flag>1</flag></object><object><points><y>0.64286</y><y>0.74026</y><x>0.74648</x><x>0.79437</x></points><label>3</label><labelname>window</labelname><flag>1</flag></object><object><points><y>0.64286</y><y>0.74242</y><x>0.68451</x><x>0.73239</x></points><label>3</label><labelname>window</labelname><flag>1</flag></object><object><points><y>0.65368</y><y>0.74459</y><x>0.39437</x><x>0.44789</x></points><label>3</label><labelname>window</labelname><flag>1</flag></object><object><points><y>0.65152</y><y>0.74459</y><x>0.32958</x><x>0.3831</x></points><label>3</label><labelname>window</labelname><flag>1</flag></object><object><points><y>0.65368</y><y>0.74459</y><x>0.25634</x><x>0.30986</x></points><label>3</label><labelname>window</labelname><flag>1</flag></object><object><points><y>0.64935</y><y>0.74242</y><x>0.19155</x><x>0.24789</x></points><label>3</label><labelname>window</labelname><flag>1</flag></object><object><points><y>0.0064935</y><y>0.045455</y><x>0.57465</x><x>0.64225</x></points><label>3</label><labelname>window</labelname><flag>1</flag></object><object><points><y>0.55844</y><y>0.57792</y><x>0.23099</x><x>0.39718</x></points><label>6</label><labelname>sill</labelname><flag>1</flag></object><object><points><y>0.55411</y><y>0.57359</y><x>0.65634</x><x>0.82254</x></points><label>6</label><labelname>sill</labelname><flag>1</flag></object><object><points><y>0.3658</y><y>0.38528</y><x>0.65915</x><x>0.82254</x></points><label>6</label><labelname>sill</labelname><flag>1</flag></object><object><points><y>0.3658</y><y>0.39394</y><x>0.1662</x><x>0.46197</x></points><label>6</label><labelname>sill</labelname><flag>1</flag></object><object><points><y>0.7381</y><y>0.75758</y><x>0.66197</x><x>0.82254</x></points><label>6</label><labelname>sill</labelname><flag>1</flag></object><object><points><y>0.74242</y><y>0.76407</y><x>0.15493</x><x>0.46761</x></points><label>6</label><labelname>sill</labelname><flag>1</flag></object><object><points><y>0.12987</y><y>0.20346</y><x>0.33239</x><x>0.39437</x></points><label>8</label><labelname>blind</labelname><flag>1</flag></object><object><points><y>0.12554</y><y>0.19264</y><x>0.51268</x><x>0.57465</x></points><label>8</label><labelname>blind</labelname><flag>1</flag></object><object><points><y>0.11905</y><y>0.18831</y><x>0.59437</x><x>0.65352</x></points><label>8</label><labelname>blind</labelname><flag>1</flag></object><object><points><y>0.11039</y><y>0.18831</y><x>0.77465</x><x>0.8338</x></points><label>8</label><labelname>blind</labelname><flag>1</flag></object><object><points><y>0.28139</y><y>0.37229</y><x>0.44225</x><x>0.49859</x></points><label>8</label><labelname>blind</labelname><flag>1</flag></object><object><points><y>0.27922</y><y>0.37229</y><x>0.12676</x><x>0.18592</x></points><label>8</label><labelname>blind</labelname><flag>1</flag></object><object><points><y>0.27922</y><y>0.37013</y><x>0.61127</x><x>0.67324</x></points><label>8</label><labelname>blind</labelname><flag>1</flag></object><object><points><y>0.27706</y><y>0.36797</y><x>0.80845</x><x>0.87042</x></points><label>8</label><labelname>blind</labelname><flag>1</flag></object><object><points><y>0.46104</y><y>0.55411</y><x>0.80563</x><x>0.86479</x></points><label>8</label><labelname>blind</labelname><flag>1</flag></object><object><points><y>0.46537</y><y>0.55628</y><x>0.61408</x><x>0.67324</x></points><label>8</label><labelname>blind</labelname><flag>1</flag></object><object><points><y>0.4697</y><y>0.56277</y><x>0.3831</x><x>0.44507</x></points><label>8</label><labelname>blind</labelname><flag>1</flag></object><object><points><y>0.47186</y><y>0.56277</y><x>0.19437</x><x>0.25634</x></points><label>8</label><labelname>blind</labelname><flag>1</flag></object><object><points><y>0.65152</y><y>0.74242</y><x>0.11549</x><x>0.17746</x></points><label>8</label><labelname>blind</labelname><flag>1</flag></object><object><points><y>0.65368</y><y>0.74675</y><x>0.44789</x><x>0.50986</x></points><label>8</label><labelname>blind</labelname><flag>1</flag></object><object><points><y>0.64502</y><y>0.74459</y><x>0.61408</x><x>0.67042</x></points><label>8</label><labelname>blind</labelname><flag>1</flag></object><object><points><y>0.64069</y><y>0.74242</y><x>0.79718</x><x>0.8507</x></points><label>8</label><labelname>blind</labelname><flag>1</flag></object><object><points><y>0.004329</y><y>0.049784</y><x>0.61127</x><x>0.65915</x></points><label>8</label><labelname>blind</labelname><flag>1</flag></object><object><points><y>0.004329</y><y>0.049784</y><x>0.55775</x><x>0.60845</x></points><label>8</label><labelname>blind</labelname><flag>1</flag></object><object><points><y>0.23377</y><y>0.28355</y><x>0.10423</x><x>0.92394</x></points><label>10</label><labelname>molding</labelname><flag>1</flag></object><object><points><y>0.74459</y><y>0.77273</y><x>0.095775</x><x>0.92394</x></points><label>10</label><labelname>molding</labelname><flag>1</flag></object><object><points><y>0.78571</y><y>0.829</y><x>0.10423</x><x>0.89577</x></points><label>12</label><labelname>shop</labelname><flag>1</flag></object><object><points><y>0.83117</y><y>0.94156</y><x>0.56338</x><x>0.84789</x></points><label>12</label><labelname>shop</labelname><flag>1</flag></object><object><points><y>0.83766</y><y>0.95455</y><x>0.39437</x><x>0.47324</x></points><label>12</label><labelname>shop</labelname><flag>1</flag></object><object><points><y>0.829</y><y>0.94589</y><x>0.21408</x><x>0.3662</x></points><label>12</label><labelname>shop</labelname><flag>1</flag></object><object><points><y>0.85065</y><y>0.9026</y><x>0.10423</x><x>0.18028</x></points><label>12</label><labelname>shop</labelname><flag>1</flag></object>
</objects>
