<objects>
<object><points><y>0.14192</y><y>0.99563</y><x>0.0015848</x><x>0.99842</x></points><label>2</label><labelname>facade</labelname><flag>1</flag></object><object><points><y>0.18996</y><y>0.28821</y><x>0.40095</x><x>0.46751</x></points><label>3</label><labelname>window</labelname><flag>1</flag></object><object><points><y>0.18777</y><y>0.28384</y><x>0.51189</x><x>0.57845</x></points><label>3</label><labelname>window</labelname><flag>1</flag></object><object><points><y>0.18996</y><y>0.28821</y><x>0.25832</x><x>0.3233</x></points><label>3</label><labelname>window</labelname><flag>1</flag></object><object><points><y>0.18996</y><y>0.28603</y><x>0.66086</x><x>0.72583</x></points><label>3</label><labelname>window</labelname><flag>1</flag></object><object><points><y>0.39956</y><y>0.49563</y><x>0.25515</x><x>0.32488</x></points><label>3</label><labelname>window</labelname><flag>1</flag></object><object><points><y>0.39738</y><y>0.49345</y><x>0.40412</x><x>0.47385</x></points><label>3</label><labelname>window</labelname><flag>1</flag></object><object><points><y>0.39738</y><y>0.49345</y><x>0.51347</x><x>0.58003</x></points><label>3</label><labelname>window</labelname><flag>1</flag></object><object><points><y>0.3952</y><y>0.49127</y><x>0.66244</x><x>0.73376</x></points><label>3</label><labelname>window</labelname><flag>1</flag></object><object><points><y>0.6048</y><y>0.69869</y><x>0.66561</x><x>0.73693</x></points><label>3</label><labelname>window</labelname><flag>1</flag></object><object><points><y>0.60044</y><y>0.69651</y><x>0.51506</x><x>0.58637</x></points><label>3</label><labelname>window</labelname><flag>1</flag></object><object><points><y>0.60044</y><y>0.69651</y><x>0.40571</x><x>0.47544</x></points><label>3</label><labelname>window</labelname><flag>1</flag></object><object><points><y>0.59825</y><y>0.69432</y><x>0.25515</x><x>0.32647</x></points><label>3</label><labelname>window</labelname><flag>1</flag></object><object><points><y>0.80131</y><y>0.89738</y><x>0.25832</x><x>0.32805</x></points><label>3</label><labelname>window</labelname><flag>1</flag></object><object><points><y>0.80568</y><y>0.89956</y><x>0.40729</x><x>0.47702</x></points><label>3</label><labelname>window</labelname><flag>1</flag></object><object><points><y>0.80349</y><y>0.89956</y><x>0.51823</x><x>0.58954</x></points><label>3</label><labelname>window</labelname><flag>1</flag></object><object><points><y>0.80349</y><y>0.89956</y><x>0.66719</x><x>0.73693</x></points><label>3</label><labelname>window</labelname><flag>1</flag></object><object><points><y>0.3952</y><y>0.49782</y><x>0.019017</x><x>0.1252</x></points><label>3</label><labelname>window</labelname><flag>1</flag></object><object><points><y>0.5917</y><y>0.69432</y><x>0.017433</x><x>0.12203</x></points><label>3</label><labelname>window</labelname><flag>1</flag></object><object><points><y>0.79258</y><y>0.8952</y><x>0.017433</x><x>0.12361</x></points><label>3</label><labelname>window</labelname><flag>1</flag></object><object><points><y>0.3952</y><y>0.49782</y><x>0.86846</x><x>0.97306</x></points><label>3</label><labelname>window</labelname><flag>1</flag></object><object><points><y>0.6048</y><y>0.70742</y><x>0.87163</x><x>0.97623</x></points><label>3</label><labelname>window</labelname><flag>1</flag></object><object><points><y>0.80349</y><y>0.90611</y><x>0.87639</x><x>0.98098</x></points><label>3</label><labelname>window</labelname><flag>1</flag></object><object><points><y>0.4869</y><y>0.50655</y><x>0.24247</x><x>0.33597</x></points><label>6</label><labelname>sill</labelname><flag>1</flag></object><object><points><y>0.4869</y><y>0.50655</y><x>0.38827</x><x>0.48019</x></points><label>6</label><labelname>sill</labelname><flag>1</flag></object><object><points><y>0.4869</y><y>0.50655</y><x>0.50396</x><x>0.59588</x></points><label>6</label><labelname>sill</labelname><flag>1</flag></object><object><points><y>0.4869</y><y>0.50655</y><x>0.65769</x><x>0.75119</x></points><label>6</label><labelname>sill</labelname><flag>1</flag></object><object><points><y>0.68777</y><y>0.70742</y><x>0.65293</x><x>0.74643</x></points><label>6</label><labelname>sill</labelname><flag>1</flag></object><object><points><y>0.68996</y><y>0.70961</y><x>0.50079</x><x>0.59271</x></points><label>6</label><labelname>sill</labelname><flag>1</flag></object><object><points><y>0.68996</y><y>0.70961</y><x>0.39461</x><x>0.48653</x></points><label>6</label><labelname>sill</labelname><flag>1</flag></object><object><points><y>0.68996</y><y>0.70961</y><x>0.24406</x><x>0.33597</x></points><label>6</label><labelname>sill</labelname><flag>1</flag></object><object><points><y>0.89301</y><y>0.91266</y><x>0.24723</x><x>0.33914</x></points><label>6</label><labelname>sill</labelname><flag>1</flag></object><object><points><y>0.89301</y><y>0.91266</y><x>0.3962</x><x>0.48811</x></points><label>6</label><labelname>sill</labelname><flag>1</flag></object><object><points><y>0.89301</y><y>0.91266</y><x>0.50713</x><x>0.59905</x></points><label>6</label><labelname>sill</labelname><flag>1</flag></object><object><points><y>0.89301</y><y>0.91266</y><x>0.65927</x><x>0.75119</x></points><label>6</label><labelname>sill</labelname><flag>1</flag></object><object><points><y>0.27511</y><y>0.29476</y><x>0.64976</x><x>0.74168</x></points><label>6</label><labelname>sill</labelname><flag>1</flag></object><object><points><y>0.27511</y><y>0.29476</y><x>0.49762</x><x>0.59113</x></points><label>6</label><labelname>sill</labelname><flag>1</flag></object><object><points><y>0.27729</y><y>0.29694</y><x>0.39303</x><x>0.48653</x></points><label>6</label><labelname>sill</labelname><flag>1</flag></object><object><points><y>0.27729</y><y>0.29694</y><x>0.2393</x><x>0.33281</x></points><label>6</label><labelname>sill</labelname><flag>1</flag></object><object><points><y>0.19214</y><y>0.28603</y><x>0.25832</x><x>0.28843</x></points><label>8</label><labelname>blind</labelname><flag>1</flag></object><object><points><y>0.19214</y><y>0.28603</y><x>0.2916</x><x>0.32013</x></points><label>8</label><labelname>blind</labelname><flag>1</flag></object><object><points><y>0.18996</y><y>0.28603</y><x>0.36767</x><x>0.40412</x></points><label>8</label><labelname>blind</labelname><flag>1</flag></object><object><points><y>0.18341</y><y>0.28384</y><x>0.4691</x><x>0.50238</x></points><label>8</label><labelname>blind</labelname><flag>1</flag></object><object><points><y>0.18996</y><y>0.28384</y><x>0.51347</x><x>0.54358</x></points><label>8</label><labelname>blind</labelname><flag>1</flag></object><object><points><y>0.18777</y><y>0.28166</y><x>0.54517</x><x>0.57686</x></points><label>8</label><labelname>blind</labelname><flag>1</flag></object><object><points><y>0.18996</y><y>0.28384</y><x>0.66244</x><x>0.69255</x></points><label>8</label><labelname>blind</labelname><flag>1</flag></object><object><points><y>0.18996</y><y>0.28384</y><x>0.69414</x><x>0.72425</x></points><label>8</label><labelname>blind</labelname><flag>1</flag></object><object><points><y>0.3952</y><y>0.48908</y><x>0.69731</x><x>0.73059</x></points><label>8</label><labelname>blind</labelname><flag>1</flag></object><object><points><y>0.3952</y><y>0.48908</y><x>0.66561</x><x>0.69572</x></points><label>8</label><labelname>blind</labelname><flag>1</flag></object><object><points><y>0.39956</y><y>0.49345</y><x>0.54834</x><x>0.58003</x></points><label>8</label><labelname>blind</labelname><flag>1</flag></object><object><points><y>0.39956</y><y>0.49127</y><x>0.51506</x><x>0.54675</x></points><label>8</label><labelname>blind</labelname><flag>1</flag></object><object><points><y>0.3952</y><y>0.49345</y><x>0.47227</x><x>0.50555</x></points><label>8</label><labelname>blind</labelname><flag>1</flag></object><object><points><y>0.3952</y><y>0.49345</y><x>0.36767</x><x>0.40254</x></points><label>8</label><labelname>blind</labelname><flag>1</flag></object><object><points><y>0.3952</y><y>0.49345</y><x>0.32647</x><x>0.36133</x></points><label>8</label><labelname>blind</labelname><flag>1</flag></object><object><points><y>0.3952</y><y>0.49345</y><x>0.22029</x><x>0.25357</x></points><label>8</label><labelname>blind</labelname><flag>1</flag></object><object><points><y>0.59607</y><y>0.69432</y><x>0.22187</x><x>0.25674</x></points><label>8</label><labelname>blind</labelname><flag>1</flag></object><object><points><y>0.60044</y><y>0.69432</y><x>0.2916</x><x>0.32647</x></points><label>8</label><labelname>blind</labelname><flag>1</flag></object><object><points><y>0.59825</y><y>0.69651</y><x>0.37084</x><x>0.40412</x></points><label>8</label><labelname>blind</labelname><flag>1</flag></object><object><points><y>0.59607</y><y>0.69432</y><x>0.47227</x><x>0.50713</x></points><label>8</label><labelname>blind</labelname><flag>1</flag></object><object><points><y>0.60262</y><y>0.69432</y><x>0.51664</x><x>0.54992</x></points><label>8</label><labelname>blind</labelname><flag>1</flag></object><object><points><y>0.60262</y><y>0.69432</y><x>0.54992</x><x>0.5832</x></points><label>8</label><labelname>blind</labelname><flag>1</flag></object><object><points><y>0.59825</y><y>0.69651</y><x>0.62916</x><x>0.66719</x></points><label>8</label><labelname>blind</labelname><flag>1</flag></object><object><points><y>0.59607</y><y>0.69651</y><x>0.73534</x><x>0.77179</x></points><label>8</label><labelname>blind</labelname><flag>1</flag></object><object><points><y>0.80349</y><y>0.8952</y><x>0.2599</x><x>0.29477</x></points><label>8</label><labelname>blind</labelname><flag>1</flag></object><object><points><y>0.80349</y><y>0.8952</y><x>0.29477</x><x>0.32647</x></points><label>8</label><labelname>blind</labelname><flag>1</flag></object><object><points><y>0.80568</y><y>0.89956</y><x>0.40887</x><x>0.44216</x></points><label>8</label><labelname>blind</labelname><flag>1</flag></object><object><points><y>0.80568</y><y>0.89956</y><x>0.44216</x><x>0.47544</x></points><label>8</label><labelname>blind</labelname><flag>1</flag></object><object><points><y>0.80568</y><y>0.89738</y><x>0.51981</x><x>0.55309</x></points><label>8</label><labelname>blind</labelname><flag>1</flag></object><object><points><y>0.80568</y><y>0.89956</y><x>0.55309</x><x>0.58637</x></points><label>8</label><labelname>blind</labelname><flag>1</flag></object><object><points><y>0.80568</y><y>0.89738</y><x>0.67036</x><x>0.70206</x></points><label>8</label><labelname>blind</labelname><flag>1</flag></object><object><points><y>0.80568</y><y>0.89738</y><x>0.70206</x><x>0.73534</x></points><label>8</label><labelname>blind</labelname><flag>1</flag></object><object><points><y>0.32314</y><y>0.37773</y><x>0.011094</x><x>0.99366</x></points><label>10</label><labelname>molding</labelname><flag>1</flag></object><object><points><y>0.15066</y><y>0.18341</y><x>0.17433</x><x>0.81616</x></points><label>10</label><labelname>molding</labelname><flag>1</flag></object>
</objects>
