<objects>
<object><points><y>0.004902</y><y>1</y><x>0.011152</x><x>0.95725</x></points><label>2</label><labelname>facade</labelname><flag>1</flag></object><object><points><y>0.21569</y><y>0.34559</y><x>0.074349</x><x>0.20632</x></points><label>3</label><labelname>window</labelname><flag>1</flag></object><object><points><y>0.22059</y><y>0.35049</y><x>0.24535</x><x>0.37732</x></points><label>3</label><labelname>window</labelname><flag>1</flag></object><object><points><y>0.22059</y><y>0.35049</y><x>0.4145</x><x>0.54647</x></points><label>3</label><labelname>window</labelname><flag>1</flag></object><object><points><y>0.22304</y><y>0.35294</y><x>0.57621</x><x>0.70632</x></points><label>3</label><labelname>window</labelname><flag>1</flag></object><object><points><y>0.22794</y><y>0.35784</y><x>0.74349</x><x>0.87361</x></points><label>3</label><labelname>window</labelname><flag>1</flag></object><object><points><y>0.51716</y><y>0.73775</y><x>0.072491</x><x>0.20632</x></points><label>3</label><labelname>window</labelname><flag>1</flag></object><object><points><y>0.51961</y><y>0.7402</y><x>0.24164</x><x>0.37546</x></points><label>3</label><labelname>window</labelname><flag>1</flag></object><object><points><y>0.52451</y><y>0.7451</y><x>0.41078</x><x>0.54461</x></points><label>3</label><labelname>window</labelname><flag>1</flag></object><object><points><y>0.52206</y><y>0.74265</y><x>0.57807</x><x>0.7119</x></points><label>3</label><labelname>window</labelname><flag>1</flag></object><object><points><y>0.52451</y><y>0.7451</y><x>0.74535</x><x>0.87732</x></points><label>3</label><labelname>window</labelname><flag>1</flag></object><object><points><y>0.52696</y><y>0.6348</y><x>0.4145</x><x>0.54089</x></points><label>8</label><labelname>blind</labelname><flag>1</flag></object><object><points><y>0.52451</y><y>0.67892</y><x>0.5855</x><x>0.70818</x></points><label>8</label><labelname>blind</labelname><flag>1</flag></object><object><points><y>0.53186</y><y>0.68137</y><x>0.75279</x><x>0.87361</x></points><label>8</label><labelname>blind</labelname><flag>1</flag></object><object><points><y>0.10539</y><y>0.15441</y><x>0.016729</x><x>0.94981</x></points><label>10</label><labelname>molding</labelname><flag>1</flag></object>
</objects>
